avss/__init__.py
avss/app.py
avss/app_factory.py
avss/connection.py
avss/http.py
avss/message_bus.py
avss/parser.py
avss/server.py
avss/settings.py
avss/scripts/start_server
avss-0.0.2.dist-info/entry_points.txt
avss-0.0.2.dist-info/LICENSE
avss-0.0.2.dist-info/WHEEL
avss-0.0.2.dist-info/METADATA
avss-0.0.2.dist-info/RECORD
