Metadata-Version: 2.1
Name: avss
Version: 0.0.2
Summary: This is a test.
Author-email: Victor Krook <victorkrook96@gmail.com>
Classifier: License :: OSI Approved :: MIT License
